captchax/__init__.py
captchax/apps.py
captchax/captcha.py
captchax/examples.py
captchax/settings.py
captchax/urls.py
captchax/utils.py
captchax/validator.py
captchax/views.py
captchax/backend/__init__.py
captchax/backend/image.py
captchax/backend/memory.py
captchax/backend/redis.py
captchax/static/fonts/dejavu-sans.ttf
drf_captchax-0.1.2.dist-info/LICENSE
drf_captchax-0.1.2.dist-info/METADATA
drf_captchax-0.1.2.dist-info/WHEEL
drf_captchax-0.1.2.dist-info/top_level.txt
drf_captchax-0.1.2.dist-info/RECORD
