Metadata-Version: 2.2
Name: drf-captchax
Version: 0.1.2
Summary: Pluggable captcha support for Django REST Framework.
Author: Alireza Alibolandi
Author-email: Alireza Alibolandi <alirezaalibolandi@duck.com>
License: MIT
Project-URL: Homepage, https://github.com/AlirezaAlibolandi/drf-captchax
Project-URL: Documentation, https://drf-captchax.readthedocs.io/
Project-URL: Source, https://github.com/AlirezaAlibolandi/drf-captchax
Project-URL: Issues, https://github.com/AlirezaAlibolandi/drf-captchax/issues
Keywords: django,django-rest-framework,captcha,security
Classifier: Development Status :: 4 - Beta
Classifier: Environment :: Web Environment
Classifier: Framework :: Django
Classifier: Framework :: Django :: 3.2
Classifier: Framework :: Django :: 4.0
Classifier: Framework :: Django :: 4.1
Classifier: Framework :: Django :: 4.2
Classifier: Intended Audience :: Developers
Classifier: License :: OSI Approved :: MIT License
Classifier: Operating System :: OS Independent
Classifier: Programming Language :: Python :: 3
Classifier: Programming Language :: Python :: 3.8
Classifier: Programming Language :: Python :: 3.9
Classifier: Programming Language :: Python :: 3.10
Classifier: Programming Language :: Python :: 3.11
Classifier: Topic :: Internet :: WWW/HTTP
Classifier: Topic :: Security
Requires-Python: >=3.8
License-File: LICENSE
Requires-Dist: Django>=3.2
Requires-Dist: djangorestframework>=3.12
Requires-Dist: Pillow>=8.0
Provides-Extra: dev
Requires-Dist: pytest>=7.0; extra == "dev"
Requires-Dist: pytest-django>=4.5; extra == "dev"
Requires-Dist: pytest-cov>=4.0; extra == "dev"
Requires-Dist: black>=23.0; extra == "dev"
Requires-Dist: isort>=5.0; extra == "dev"
Requires-Dist: flake8>=6.0; extra == "dev"
Requires-Dist: mypy>=1.0; extra == "dev"
Provides-Extra: docs
Requires-Dist: sphinx>=4.0; extra == "docs"
Requires-Dist: sphinx-rtd-theme>=1.0; extra == "docs"
Dynamic: author
